.git_archival.txt
.gitattributes
.gitignore
.readthedocs.yml
CHANGES.rst
LICENSE.rst
README.md
pyproject.toml
requirements.txt
setup.cfg
setup.py
.github/dependabot.yml
.github/workflows/linting.yaml
.github/workflows/monthly-warning-test.yaml
.github/workflows/tests.yaml
diffmah/__init__.py
diffmah/_version.py
diffmah/defaults.py
diffmah/diffmah_kernels.py
diffmah/utils.py
diffmah.egg-info/PKG-INFO
diffmah.egg-info/SOURCES.txt
diffmah.egg-info/dependency_links.txt
diffmah.egg-info/requires.txt
diffmah.egg-info/top_level.txt
diffmah/data/README.txt
diffmah/data/__init__.py
diffmah/data_loaders/README.txt
diffmah/data_loaders/__init__.py
diffmah/data_loaders/load_diffmah_pub_data.py
diffmah/data_loaders/load_galacticus_eps_mahs.py
diffmah/data_loaders/load_hacc_mahs.py
diffmah/data_loaders/load_tng_mahs.py
diffmah/data_loaders/tests/__init__.py
diffmah/data_loaders/tests/test_load_diffmah_pub_data.py
diffmah/diffmahpop_kernels/__init__.py
diffmah/diffmahpop_kernels/bimod_cens_fithelp.py
diffmah/diffmahpop_kernels/bimod_censat_fithelp.py
diffmah/diffmahpop_kernels/bimod_censat_params.py
diffmah/diffmahpop_kernels/bimod_sats_fithelp.py
diffmah/diffmahpop_kernels/covariance_kernels.py
diffmah/diffmahpop_kernels/early_index_alpha.py
diffmah/diffmahpop_kernels/early_index_beta.py
diffmah/diffmahpop_kernels/early_index_bimod.py
diffmah/diffmahpop_kernels/early_index_pop.py
diffmah/diffmahpop_kernels/frac_early_cens.py
diffmah/diffmahpop_kernels/ftpt0_cens.py
diffmah/diffmahpop_kernels/late_index_alpha.py
diffmah/diffmahpop_kernels/late_index_beta.py
diffmah/diffmahpop_kernels/late_index_bimod.py
diffmah/diffmahpop_kernels/load_diffmahpop_fitdata.py
diffmah/diffmahpop_kernels/logtc_bimod.py
diffmah/diffmahpop_kernels/logtc_early.py
diffmah/diffmahpop_kernels/logtc_late.py
diffmah/diffmahpop_kernels/mc_bimod_cens.py
diffmah/diffmahpop_kernels/mc_bimod_sats.py
diffmah/diffmahpop_kernels/param_utils.py
diffmah/diffmahpop_kernels/bimod_logm0_kernels/__init__.py
diffmah/diffmahpop_kernels/bimod_logm0_kernels/logm0_c0_early.py
diffmah/diffmahpop_kernels/bimod_logm0_kernels/logm0_c0_late.py
