Metadata-Version: 2.4
Name: diffmah
Version: 0.7.3
Summary: Differentiable model of dark matter halo assembly
Author-email: Andrew Hearin <ahearin@anl.gov>
License: BSD 3-Clause License
Project-URL: home, https://github.com/ArgonneCPAC/diffmah
Classifier: Programming Language :: Python :: 3
Requires-Python: >=3.11
License-File: LICENSE.rst
Requires-Dist: numpy
Requires-Dist: jax
Dynamic: license-file
